degel_python_utils/__init__.py
degel_python_utils/py.typed
degel_python_utils/data/__init__.py
degel_python_utils/data/read_table.py
degel_python_utils/data/write_table.py
degel_python_utils/sys_utils/__init__.py
degel_python_utils/sys_utils/env.py
degel_python_utils/sys_utils/errors.py
degel_python_utils/sys_utils/file_system.py
degel_python_utils/sys_utils/log_tools.py
degel_python_utils/sys_utils/typing_helpers.py
degel_python_utils-1.0.2.dist-info/LICENSE
degel_python_utils-1.0.2.dist-info/METADATA
degel_python_utils-1.0.2.dist-info/WHEEL
degel_python_utils-1.0.2.dist-info/top_level.txt
degel_python_utils-1.0.2.dist-info/RECORD
