Metadata-Version: 2.2
Name: degel-python-utils
Version: 1.0.2
Summary: Shared Python utilities from Degel Software Ltd.
Home-page: https://github.com/deg/degel-python-utils
Author: David Goldfarb
Author-email: deg@degel.com
Classifier: Programming Language :: Python :: 3.12
Classifier: License :: OSI Approved :: MIT License
Classifier: Operating System :: OS Independent
Requires-Python: >=3.10
License-File: LICENSE
Requires-Dist: blessings
Requires-Dist: fastapi
Requires-Dist: google-search-results
Requires-Dist: openpyxl
Requires-Dist: python-multipart
Requires-Dist: requests
Requires-Dist: uvicorn
Provides-Extra: dev
Requires-Dist: black; extra == "dev"
Requires-Dist: build; extra == "dev"
Requires-Dist: flake8; extra == "dev"
Requires-Dist: flake8-annotations; extra == "dev"
Requires-Dist: ghp-import; extra == "dev"
Requires-Dist: line-profiler; extra == "dev"
Requires-Dist: mypy; extra == "dev"
Requires-Dist: pdoc; extra == "dev"
Requires-Dist: pre-commit; extra == "dev"
Requires-Dist: pylint; extra == "dev"
Requires-Dist: pylint-pydantic; extra == "dev"
Requires-Dist: pytest; extra == "dev"
Requires-Dist: pytest-mock; extra == "dev"
Requires-Dist: setuptools; extra == "dev"
Requires-Dist: twine; extra == "dev"
Requires-Dist: wheel; extra == "dev"
